pyaltherma/__init__.py
pyaltherma/comm.py
pyaltherma/const.py
pyaltherma/controllers.py
pyaltherma/errors.py
pyaltherma/profile.py
pyaltherma/proto.py
pyaltherma/utils.py
pyaltherma-0.0.21.dist-info/LICENSE
pyaltherma-0.0.21.dist-info/WHEEL
pyaltherma-0.0.21.dist-info/METADATA
pyaltherma-0.0.21.dist-info/RECORD
