Metadata-Version: 2.1
Name: pyaltherma
Version: 0.0.21
Summary: Python scripts for controlling Daikin Altherma heat pump using BRP069A62 LAN adapter.
Home-page: https://github.com/tadasdanielius/pyaltherma
License: MIT
Keywords: daikin,altherma,heatpump,brp069A62,brp069A61
Author: Tadas Danielius
Requires-Python: >=3.7,<4.0
Classifier: Development Status :: 3 - Alpha
Classifier: License :: OSI Approved :: MIT License
Classifier: Programming Language :: Python :: 3
Classifier: Programming Language :: Python :: 3.10
Classifier: Programming Language :: Python :: 3.7
Classifier: Programming Language :: Python :: 3.8
Classifier: Programming Language :: Python :: 3.9
Requires-Dist: aiohttp (>=3.7.4,<4.0.0)
Project-URL: Repository, https://github.com/tadasdanielius/pyaltherma
